{"type":"APL","version":"1.5","mainTemplate":{"items":[{"type":"Container","direction":"column","height":"100vh","width":"100vw","items":[{"type":"AlexaBackground","backgroundColor":"#192f57","backgroundGradient":{"type":"linear","colorRange":["#0e1c36","#192f57"],"inputRange":[0,1],"angle":0}},{"type":"Container","direction":"column","justifyContent":"center","alignItems":"center","height":"100%","items":[{"type":"AlexaHeader","headerTitle":"Mi Habilidad","headerAttributionImage":"URL_DE_LA_IMAGEN","headerAttributionPrimacy":false},{"type":"Container","direction":"row","justifyContent":"spaceBetween","alignItems":"center","grow":1,"paddingTop":"20px","paddingBottom":"20px","items":[{"type":"Image","source":"https://img.freepik.com/vector-premium/imagen-dibujos-animados-hongo-palabra-hongo_587001-200.jpg?w=2000","width":"45vw","height":"100vh","when":"${viewport.width >= 768}","align":"left"},{"type":"Text","text":"jiji","fontSize":"20px","paddingLeft":"20px","color":"white","grow":1}]},{"type":"Text","text":"hola","fontSize":"30px","paddingTop":"20px","color":"white","grow":1},{"type":"AlexaFooter","footerHint":"Hint del pie de página","color":"white","when":"${viewport.width >= 768}"}]}]}]}}